{
    "overall_score": 0.04,
    "problems": [
        {
            "macro-f1": 0.11,
            "macro-precision": 0.223,
            "macro-recall": 0.098,
            "problem-name": "problem00001"
        },
        {
            "macro-f1": 0.01,
            "macro-precision": 0.056,
            "macro-recall": 0.006,
            "problem-name": "problem00002"
        },
        {
            "macro-f1": 0.045,
            "macro-precision": 0.082,
            "macro-recall": 0.031,
            "problem-name": "problem00003"
        },
        {
            "macro-f1": 0.013,
            "macro-precision": 0.063,
            "macro-recall": 0.007,
            "problem-name": "problem00004"
        },
        {
            "macro-f1": 0.079,
            "macro-precision": 0.084,
            "macro-recall": 0.076,
            "problem-name": "problem00005"
        },
        {
            "macro-f1": 0.047,
            "macro-precision": 0.106,
            "macro-recall": 0.031,
            "problem-name": "problem00006"
        },
        {
            "macro-f1": 0.0,
            "macro-precision": 0.0,
            "macro-recall": 0.0,
            "problem-name": "problem00007"
        },
        {
            "macro-f1": 0.039,
            "macro-precision": 0.042,
            "macro-recall": 0.058,
            "problem-name": "problem00008"
        },
        {
            "macro-f1": 0.0,
            "macro-precision": 0.0,
            "macro-recall": 0.0,
            "problem-name": "problem00009"
        },
        {
            "macro-f1": 0.0,
            "macro-precision": 0.0,
            "macro-recall": 0.0,
            "problem-name": "problem00010"
        },
        {
            "macro-f1": 0.078,
            "macro-precision": 0.064,
            "macro-recall": 0.101,
            "problem-name": "problem00011"
        },
        {
            "macro-f1": 0.038,
            "macro-precision": 0.167,
            "macro-recall": 0.022,
            "problem-name": "problem00012"
        },
        {
            "macro-f1": 0.049,
            "macro-precision": 0.135,
            "macro-recall": 0.059,
            "problem-name": "problem00013"
        },
        {
            "macro-f1": 0.078,
            "macro-precision": 0.222,
            "macro-recall": 0.049,
            "problem-name": "problem00014"
        },
        {
            "macro-f1": 0.056,
            "macro-precision": 0.037,
            "macro-recall": 0.111,
            "problem-name": "problem00015"
        },
        {
            "macro-f1": 0.044,
            "macro-precision": 0.167,
            "macro-recall": 0.026,
            "problem-name": "problem00016"
        },
        {
            "macro-f1": 0.03,
            "macro-precision": 0.167,
            "macro-recall": 0.016,
            "problem-name": "problem00017"
        },
        {
            "macro-f1": 0.006,
            "macro-precision": 0.004,
            "macro-recall": 0.01,
            "problem-name": "problem00018"
        },
        {
            "macro-f1": 0.011,
            "macro-precision": 0.074,
            "macro-recall": 0.006,
            "problem-name": "problem00019"
        },
        {
            "macro-f1": 0.076,
            "macro-precision": 0.073,
            "macro-recall": 0.083,
            "problem-name": "problem00020"
        }
    ]
}